slippistats/__init__.py
slippistats/controller.py
slippistats/event.py
slippistats/game.py
slippistats/log.py
slippistats/metadata.py
slippistats/parse.py
slippistats/util.py
slippistats/enums/__init__.py
slippistats/enums/attack.py
slippistats/enums/character.py
slippistats/enums/item.py
slippistats/enums/stage.py
slippistats/enums/state.py
slippistats/stats/__init__.py
slippistats/stats/combo_computer.py
slippistats/stats/common.py
slippistats/stats/computer.py
slippistats/stats/stat_types.py
slippistats/stats/stats_computer.py
test/__init__.py
test/replays_test.py
slippistats-0.1.3.dist-info/LICENSE.txt
slippistats-0.1.3.dist-info/METADATA
slippistats-0.1.3.dist-info/WHEEL
slippistats-0.1.3.dist-info/top_level.txt
slippistats-0.1.3.dist-info/RECORD
