Metadata-Version: 2.1
Name: slippistats
Version: 0.1.3
Summary: Stats library for SSBM replay files
Author-email: Walnut356 <walnut356@gmail.com>
License: MIT License
Classifier: Programming Language :: Python :: 3
Classifier: License :: OSI Approved :: MIT License
Classifier: Operating System :: OS Independent
Requires-Python: >=3.10
License-File: LICENSE.txt
Requires-Dist: py-ubjson (~=0.16)
Requires-Dist: tzlocal (~=4.3)
Requires-Dist: polars (~=0.17.9)
